{
  "diseases": [
    {
      "id": 1,
      "name": "Foot and Mouth Disease",
      "scientific_name": "Aphthae epizooticae",
      "species": ["Cattle", "Sheep", "Goats"],
      "symptoms": "Fever, blisters in mouth and feet, lameness, excessive salivation, loss of appetite",
      "causes": "Virus transmission through contact, contaminated feed/water",
      "prevention": "Vaccination, biosecurity measures, quarantine new animals",
      "treatment": "Supportive care, antibiotic treatment for secondary infections, isolation",
      "severity": "High",
      "contagious": true,
      "mortality_rate": "Low (1-5%)",
      "affected_body_parts": "Mouth, feet, udder",
      "seasonality": "All year, peaks in dry season",
      "model_confidence_threshold": 0.8
    },
    {
      "id": 2,
      "name": "Mastitis",
      "scientific_name": "Mammary gland inflammation",
      "species": ["Cattle"],
      "symptoms": "Swollen udder, abnormal milk (clots, blood), fever, loss of appetite",
      "causes": "Bacterial infection, poor milking hygiene, stress",
      "prevention": "Proper milking hygiene, clean bedding, regular udder health checks",
      "treatment": "Antibiotic treatment, anti-inflammatory drugs, milking hygiene",
      "severity": "Medium",
      "contagious": false,
      "mortality_rate": "Very low",
      "affected_body_parts": "Udder, mammary glands",
      "seasonality": "All year",
      "model_confidence_threshold": 0.7
    },
    {
      "id": 3,
      "name": "Lumpy Skin Disease",
      "scientific_name": "Neethling virus infection",
      "species": ["Cattle"],
      "symptoms": "Firm nodules on skin, fever, reduced milk production, loss of appetite",
      "causes": "Virus transmission by insects, contact with infected animals",
      "prevention": "Vaccination, vector control, quarantine new animals",
      "treatment": "Supportive care, antibiotic treatment for secondary infections",
      "severity": "High",
      "contagious": true,
      "mortality_rate": "Low (1-5%)",
      "affected_body_parts": "Skin, lymph nodes",
      "seasonality": "Peaks in rainy season",
      "model_confidence_threshold": 0.8
    },
    {
      "id": 4,
      "name": "Blackleg",
      "scientific_name": "Clostridium chauvoei infection",
      "species": ["Cattle", "Sheep"],
      "symptoms": "Sudden death, lameness, swelling in muscles, fever, depression",
      "causes": "Bacterial spores in soil, wounds, deep muscle injuries",
      "prevention": "Vaccination, avoid deep wounds, proper wound care",
      "treatment": "Emergency vaccination, antibiotic treatment, surgical drainage",
      "severity": "Critical",
      "contagious": false,
      "mortality_rate": "High (80-100%)",
      "affected_body_parts": "Muscles, particularly legs",
      "seasonality": "All year, peaks in wet season",
      "model_confidence_threshold": 0.9
    },
    {
      "id": 5,
      "name": "Anthrax",
      "scientific_name": "Bacillus anthracis infection",
      "species": ["Cattle", "Sheep", "Goats"],
      "symptoms": "Sudden death, bleeding from body openings, high fever, difficulty breathing",
      "causes": "Bacterial spores in soil, contaminated feed/water",
      "prevention": "Vaccination, avoid contaminated areas, proper carcass disposal",
      "treatment": "Immediate veterinary attention, antibiotic treatment, isolation",
      "severity": "Critical",
      "contagious": true,
      "mortality_rate": "High (90-100%)",
      "affected_body_parts": "Multiple organs, blood",
      "seasonality": "All year, peaks in dry season",
      "model_confidence_threshold": 0.9
    },
    {
      "id": 6,
      "name": "Pneumonia",
      "scientific_name": "Respiratory tract infection",
      "species": ["Cattle", "Sheep", "Goats"],
      "symptoms": "Coughing, difficulty breathing, fever, nasal discharge, loss of appetite",
      "causes": "Bacterial or viral infection, poor ventilation, stress",
      "prevention": "Good ventilation, proper nutrition, stress reduction, vaccination",
      "treatment": "Antibiotic treatment, anti-inflammatory drugs, supportive care",
      "severity": "Medium",
      "contagious": true,
      "mortality_rate": "Low to moderate (5-20%)",
      "affected_body_parts": "Lungs, respiratory system",
      "seasonality": "All year, peaks in cold season",
      "model_confidence_threshold": 0.7
    },
    {
      "id": 7,
      "name": "Mange",
      "scientific_name": "Sarcoptic mange",
      "species": ["Cattle", "Sheep", "Goats"],
      "symptoms": "Itching, hair loss, skin thickening, restlessness, weight loss",
      "causes": "Mite infestation, poor hygiene, overcrowding",
      "prevention": "Regular health checks, quarantine new animals, clean environment",
      "treatment": "Acaricide treatment, environmental cleaning, isolation",
      "severity": "Low",
      "contagious": true,
      "mortality_rate": "Very low",
      "affected_body_parts": "Skin, hair follicles",
      "seasonality": "All year",
      "model_confidence_threshold": 0.6
    },
    {
      "id": 8,
      "name": "Ringworm",
      "scientific_name": "Dermatophytosis",
      "species": ["Cattle", "Sheep", "Goats"],
      "symptoms": "Circular lesions, hair loss, scaly skin, mild itching",
      "causes": "Fungal infection, poor hygiene, stress",
      "prevention": "Good hygiene, avoid contact with infected animals, clean environment",
      "treatment": "Antifungal treatment, topical medication, environmental cleaning",
      "severity": "Low",
      "contagious": true,
      "mortality_rate": "None",
      "affected_body_parts": "Skin, hair",
      "seasonality": "All year",
      "model_confidence_threshold": 0.6
    },
    {
      "id": 9,
      "name": "Bloat",
      "scientific_name": "Ruminal tympany",
      "species": ["Cattle", "Sheep", "Goats"],
      "symptoms": "Distended abdomen, difficulty breathing, restlessness, loss of appetite",
      "causes": "Fermentation gas accumulation, diet changes, obstruction",
      "prevention": "Proper feeding management, avoid sudden diet changes, monitor grazing",
      "treatment": "Emergency treatment, stomach tube, anti-foaming agents",
      "severity": "Medium",
      "contagious": false,
      "mortality_rate": "Moderate (20-50%)",
      "affected_body_parts": "Stomach, digestive system",
      "seasonality": "All year",
      "model_confidence_threshold": 0.7
    },
    {
      "id": 10,
      "name": "Healthy",
      "scientific_name": "Normal physiological state",
      "species": ["All"],
      "symptoms": "No symptoms observed",
      "causes": "Normal health status",
      "prevention": "Continue current health management practices",
      "treatment": "Continue regular health monitoring",
      "severity": "None",
      "contagious": false,
      "mortality_rate": "None",
      "affected_body_parts": "None",
      "seasonality": "All year",
      "model_confidence_threshold": 0.5
    }
  ],
  "model_info": {
    "version": "1.0.0",
    "input_size": 224,
    "num_classes": 10,
    "classes": [
      "Foot and Mouth Disease",
      "Mastitis", 
      "Lumpy Skin Disease",
      "Blackleg",
      "Anthrax",
      "Pneumonia",
      "Healthy",
      "Mange",
      "Ringworm",
      "Bloat"
    ],
    "confidence_threshold": 0.7,
    "created_date": "2023-12-01",
    "description": "Livestock disease detection model trained on agricultural images"
  }
}
